{
    "id": "Blog_core_c292363b-37a4-4964-9905-6de06d25adf3",
    "type": "Blog",
    "name": "Sustainable Coffee for you",
    "description": "Good for the heart and soul",
    "createddate": {
        "value": "2017-05-08T22:15:44.823Z",
        "timezone": "UTC",
        "description": ""
    },
    "updateddate": {
        "value": "2017-08-03T07:22:23.192Z",
        "timezone": "UTC",
        "description": ""
    },
    "links": [{
        "href": "https://demo-gse00009991.sites.us2.oraclecloud.com:443/content/published/api/v1/items/Blog_core_c292363b-37a4-4964-9905-6de06d25adf3",
        "rel": "self",
        "templated": false,
        "method": "GET",
        "profile": "",
        "mediaType": ""
    }, {
        "href": "https://demo-gse00009991.sites.us2.oraclecloud.com:443/content/published/api/v1/items/Blog_core_c292363b-37a4-4964-9905-6de06d25adf3",
        "rel": "canonical",
        "templated": false,
        "method": "GET",
        "profile": "",
        "mediaType": ""
    }, {
        "href": "https://demo-gse00009991.sites.us2.oraclecloud.com:443/content/published/api/v1/metadata-catalog/items/Blog_core_c292363b-37a4-4964-9905-6de06d25adf3",
        "rel": "describedby",
        "templated": false,
        "method": "GET",
        "profile": "",
        "mediaType": "application/schema+json"
    }],
    "data": {
        "blog_category": "DRINKS",
        "blog_textposition": "Center",
        "blog_textcolor": "Light",
        "blog_content": "<p>Our coffee comes from South American regions where we have a strong commitment to supporting the farming communities that supply our coffee, tea and cocoa, and other agricultural products.&nbsp; Experience our famous Aroma coffee roast today. Our coffee comes from South American regions where we have a strong commitment to supporting the farming communities that supply our coffee, tea and cocoa, and other agricultural products.&nbsp; Experience our famous Aroma coffee roast today.<o:p></o:p></p>\n\n<p><o:p>&nbsp;</o:p></p>\n\n<p>Our coffee comes from South African regions where we have a strong commitment to supporting the farming communities that supply our coffee, tea and cocoa, and other agricultural products.&nbsp; Experience our famous Aroma coffee roast today. ​Our coffee comes from South American regions where we have a strong commitment to supporting the farming communities that supply our coffee, tea and cocoa, and other agricultural products. <o:p></o:p></p>\n\n<p><o:p>&nbsp;</o:p></p>\n\n<p>Our coffee comes from South American regions where we have a strong commitment to supporting the farming communities that supply our coffee, tea and cocoa, and other agricultural products.&nbsp; Experience our famous Aroma coffee roast today. ​Our coffee comes from South American regions where we have a strong commitment to supporting the farming communities that supply our coffee, tea and cocoa, and other agricultural products.&nbsp; Experience our famous Aroma coffee roast today.<o:p></o:p></p>\n",
        "blog_image_ad": {
            "id": "DigitalAsset_proxy_65418071-9e7e-4ff5-a2a6-7513832106e1",
            "type": "DigitalAsset",
            "link": {
                "href": "https://demo-gse00009991.sites.us2.oraclecloud.com:443/content/published/api/v1/items/DigitalAsset_proxy_65418071-9e7e-4ff5-a2a6-7513832106e1",
                "rel": "Reference",
                "templated": false,
                "method": "GET",
                "profile": "",
                "mediaType": ""
            }
        },
        "blog_image_thumbnail": {
            "id": "DigitalAsset_proxy_e156c1a8-7f02-4e9d-b9bb-7a63077cea3c",
            "type": "DigitalAsset",
            "link": {
                "href": "https://demo-gse00009991.sites.us2.oraclecloud.com:443/content/published/api/v1/items/DigitalAsset_proxy_e156c1a8-7f02-4e9d-b9bb-7a63077cea3c",
                "rel": "Reference",
                "templated": false,
                "method": "GET",
                "profile": "",
                "mediaType": ""
            }
        },
        "blog_image_header": {
            "id": "DigitalAsset_proxy_43822e3b-c719-43b2-b93a-4ec86f623e36",
            "type": "DigitalAsset",
            "link": {
                "href": "https://demo-gse00009991.sites.us2.oraclecloud.com:443/content/published/api/v1/items/DigitalAsset_proxy_43822e3b-c719-43b2-b93a-4ec86f623e36",
                "rel": "Reference",
                "templated": false,
                "method": "GET",
                "profile": "",
                "mediaType": ""
            }
        },
        "blog_image_ad_small": {
            "id": "DigitalAsset_proxy_d3a8a531-5a1a-4ef8-ad69-6105702037cd",
            "type": "DigitalAsset",
            "link": {
                "href": "https://demo-gse00009991.sites.us2.oraclecloud.com:443/content/published/api/v1/items/DigitalAsset_proxy_d3a8a531-5a1a-4ef8-ad69-6105702037cd",
                "rel": "Reference",
                "templated": false,
                "method": "GET",
                "profile": "",
                "mediaType": ""
            }
        },
        "blog_author": {
            "id": "Author_core_53dba240-c673-4c2b-9623-d2bbff990e6d",
            "type": "Author",
            "link": {
                "href": "https://demo-gse00009991.sites.us2.oraclecloud.com:443/content/published/api/v1/items/Author_core_53dba240-c673-4c2b-9623-d2bbff990e6d",
                "rel": "Reference",
                "templated": false,
                "method": "GET",
                "profile": "",
                "mediaType": ""
            }
        }
    },
    "publishinfo": [{
        "target": "F7F68BC5467313FACB749F39ECCA8B41B03C8311AD5D",
        "publishedby": "1463671286774",
        "version": "3",
        "publisheddate": {
            "value": "2017-08-03T07:22:21.827Z",
            "timezone": "UTC",
            "description": ""
        }
    }],
    "externalFile": {
        "folderId": "FE8BC00389973E65510604A5ECCA8B41B03C8311AD5D",
        "fileId": "DB691D737D80CB95E626402BECCA8B41B03C8311AD5D",
        "version": "3"
    }
}